rocketchat/__init__.py
rocketchat/rocketchat.py
rocketchat-1.0.0.dist-info/LICENSE
rocketchat-1.0.0.dist-info/WHEEL
rocketchat-1.0.0.dist-info/METADATA
rocketchat-1.0.0.dist-info/RECORD
